nukat/__init__.py
nukat/client.py
nukat/main.py
nukat-1.0.0.dist-info/licenses/LICENSE
nukat-1.0.0.dist-info/METADATA
nukat-1.0.0.dist-info/WHEEL
nukat-1.0.0.dist-info/entry_points.txt
nukat-1.0.0.dist-info/top_level.txt
nukat-1.0.0.dist-info/RECORD
